KINCluster/KINCluster.py
KINCluster/__init__.py
KINCluster/settings.py
KINCluster/core/__init__.py
KINCluster/core/cluster.py
KINCluster/core/extractor.py
KINCluster/core/item.py
KINCluster/core/pipeline.py
KINCluster/lib/__init__.py
KINCluster/lib/stopwords.py
KINCluster/lib/tokenizer.py
KINCluster/lib/stopwords/stopwords-ko.txt
KINCluster-0.2.0.dist-info/LICENSE
KINCluster-0.2.0.dist-info/METADATA
KINCluster-0.2.0.dist-info/WHEEL
KINCluster-0.2.0.dist-info/entry_points.txt
KINCluster-0.2.0.dist-info/top_level.txt
KINCluster-0.2.0.dist-info/RECORD
