Metadata-Version: 2.1
Name: KINCluster
Version: 0.2.0
Summary: Korean Involute News Cluster
Home-page: https://github.com/MaybeS/KINCluster
Author: Bae jiun
Author-email: alice.maydev@gmail.com
License: MIT
Keywords: KINCluster,cluster,documentsdoc2vec,tokenize,korean
Platform: UNKNOWN
Classifier: Programming Language :: Python :: 3.5
Classifier: Programming Language :: Python :: 3.6
Classifier: Programming Language :: Python :: 3.7
Classifier: Programming Language :: Python :: 3.8
Classifier: Programming Language :: Python :: 3.9
License-File: LICENSE
Requires-Dist: JPype1 (==1.4.0)
Requires-Dist: konlpy (==0.6.0)
Requires-Dist: scipy (==1.8.0)
Requires-Dist: numpy (>=1.21.6)
Requires-Dist: gensim (==4.2.0)
